bitsio/__init__.py
bitsio/_version.py
bitsio/bitsio.py
bitsio-1.0.0.dist-info/LICENSE
bitsio-1.0.0.dist-info/METADATA
bitsio-1.0.0.dist-info/WHEEL
bitsio-1.0.0.dist-info/top_level.txt
bitsio-1.0.0.dist-info/RECORD
