Metadata-Version: 2.1
Name: bitsio
Version: 1.0.0
Summary: The BitsIO is a bit stream I/O class.
Home-page: https://github.com/m-hiki/bitsio
Author: Minoru Hiki
Author-email: minoruhiki@gmail.com
License: MIT License
Keywords: bitstream,io
Platform: UNKNOWN
Requires-Python: >=3.4
